deepcodec/__init__.pxd
deepcodec/__init__.py
deepcodec/__main__.py
deepcodec/_core.cpython-311-aarch64-linux-gnu.so
deepcodec/_core.pyi
deepcodec/about.py
deepcodec/bitstream.cpython-311-aarch64-linux-gnu.so
deepcodec/bitstream.pxd
deepcodec/bitstream.pyi
deepcodec/buffer.cpython-311-aarch64-linux-gnu.so
deepcodec/buffer.pxd
deepcodec/buffer.pyi
deepcodec/bytesource.cpython-311-aarch64-linux-gnu.so
deepcodec/bytesource.pxd
deepcodec/datasets.py
deepcodec/descriptor.cpython-311-aarch64-linux-gnu.so
deepcodec/descriptor.pxd
deepcodec/descriptor.pyi
deepcodec/dictionary.cpython-311-aarch64-linux-gnu.so
deepcodec/dictionary.pxd
deepcodec/dictionary.pyi
deepcodec/error.cpython-311-aarch64-linux-gnu.so
deepcodec/error.pxd
deepcodec/error.pyi
deepcodec/format.cpython-311-aarch64-linux-gnu.so
deepcodec/format.pxd
deepcodec/format.pyi
deepcodec/frame.cpython-311-aarch64-linux-gnu.so
deepcodec/frame.pxd
deepcodec/frame.pyi
deepcodec/logging.cpython-311-aarch64-linux-gnu.so
deepcodec/logging.pxd
deepcodec/logging.pyi
deepcodec/opaque.cpython-311-aarch64-linux-gnu.so
deepcodec/opaque.pxd
deepcodec/option.cpython-311-aarch64-linux-gnu.so
deepcodec/option.pxd
deepcodec/option.pyi
deepcodec/packet.cpython-311-aarch64-linux-gnu.so
deepcodec/packet.pxd
deepcodec/packet.py
deepcodec/packet.pyi
deepcodec/plane.cpython-311-aarch64-linux-gnu.so
deepcodec/plane.pxd
deepcodec/plane.pyi
deepcodec/py.typed
deepcodec/stream.cpython-311-aarch64-linux-gnu.so
deepcodec/stream.pxd
deepcodec/stream.pyi
deepcodec/utils.cpython-311-aarch64-linux-gnu.so
deepcodec/utils.pxd
deepcodec/vfast.cpython-311-aarch64-linux-gnu.so
deepcodec/vfast.py
deepcodec/attachments/__init__.py
deepcodec/attachments/stream.cpython-311-aarch64-linux-gnu.so
deepcodec/attachments/stream.pxd
deepcodec/attachments/stream.pyi
deepcodec/audio/__init__.pxd
deepcodec/audio/__init__.py
deepcodec/audio/__init__.pyi
deepcodec-0.0.8.dist-info/METADATA
deepcodec-0.0.8.dist-info/WHEEL
deepcodec-0.0.8.dist-info/entry_points.txt
deepcodec-0.0.8.dist-info/top_level.txt
deepcodec-0.0.8.dist-info/RECORD
deepcodec-0.0.8.dist-info/licenses/LICENSE.txt
